{
  "project_info": {
    "project_number": "342780061252",
    "project_id": "world-s-hardest-game",
    "storage_bucket": "world-s-hardest-game.firebasestorage.app"
  },
  "client": [
    {
      "client_info": {
        "mobilesdk_app_id": "1:342780061252:android:3b42d14d0c84b767333e11",
        "android_client_info": {
          "package_name": "com.example.worldshardestgame_multiplayer"
        }
      },
      "oauth_client": [],
      "api_key": [
        {
          "current_key": "AIzaSyA8D0HFaa-QZ3nqkIot5Hn8JOA-FEo_FL0"
        }
      ],
      "services": {
        "appinvite_service": {
          "other_platform_oauth_client": []
        }
      }
    }
  ],
  "configuration_version": "1"
}